augmentation/__init__.py
augmentation/augmentation.py
callbacks/__init__.py
callbacks/callbacks.py
hyso-0.1.2.dist-info/licenses/LICENSE
models/WithSE.py
models/__init__.py
models/bcam.py
models/fit.py
hyso-0.1.2.dist-info/METADATA
hyso-0.1.2.dist-info/WHEEL
hyso-0.1.2.dist-info/top_level.txt
hyso-0.1.2.dist-info/RECORD
