Metadata-Version: 2.4
Name: hyso
Version: 0.1.2
Summary: Hyso: Custom CNN models, SE/CBAM blocks, callbacks, and augmentations
Home-page: https://github.com/huseyin-dgn/hyso
Author: Huseyin Dogan
Author-email: hdgn5838@gmial.com
License: MIT
Classifier: Programming Language :: Python :: 3
Classifier: License :: OSI Approved :: MIT License
Classifier: Operating System :: OS Independent
Requires-Python: >=3.8
License-File: LICENSE
Requires-Dist: torch>=1.13
Requires-Dist: torchvision>=0.14
Requires-Dist: numpy
Requires-Dist: matplotlib
Requires-Dist: seaborn
Requires-Dist: scikit-learn
Requires-Dist: tqdm
Dynamic: license-file
